picsexl/__init__.py
picsexl/picsexl.py
picsexl/excelwriter/__init__.py
picsexl/excelwriter/constants.py
picsexl/excelwriter/excelwriter.py
picsexl/excelwriter/exceptions.py
picsexl/icsreader/__init__.py
picsexl/icsreader/exceptions.py
picsexl/icsreader/icsreader.py
picsexl/icssniffer/__init__.py
picsexl/icssniffer/exceptions.py
picsexl/icssniffer/icssniffer.py
picsexl-0.1.4.dist-info/LICENSE
picsexl-0.1.4.dist-info/METADATA
picsexl-0.1.4.dist-info/WHEEL
picsexl-0.1.4.dist-info/top_level.txt
picsexl-0.1.4.dist-info/RECORD
