Metadata-Version: 2.1
Name: picsexl
Version: 0.1.4
Summary: Converter from ics format to xls
Home-page: https://github.com/pog7x/picsexl
Author: pog7x
Author-email: poluningm@gmail.com
License: MIT
Keywords: python calendar ics excel recurring
Classifier: License :: OSI Approved :: MIT License
Classifier: Operating System :: OS Independent
Classifier: Programming Language :: Python
Classifier: Programming Language :: Python :: 3.7
Classifier: Programming Language :: Python :: 3.8
Classifier: Programming Language :: Python :: 3.9
Classifier: Programming Language :: Python :: 3.10
Classifier: Programming Language :: Python :: 3.11
Classifier: Programming Language :: Python :: Implementation :: CPython
Classifier: Programming Language :: Python :: Implementation :: PyPy
Requires-Python: >=3.7
License-File: LICENSE
Requires-Dist: icalendar (==5.0.2)
Requires-Dist: openpyxl (==3.0.10)
Requires-Dist: python-dateutil (==2.8.2)
Requires-Dist: pytz (==2022.7.1)
